filmtrfkeras/__init__.py
filmtrfkeras/cli.py
filmtrfkeras/filmtrfkeras.py
filmtrfkeras-0.0.1.dist-info/METADATA
filmtrfkeras-0.0.1.dist-info/WHEEL
filmtrfkeras-0.0.1.dist-info/entry_points.txt
filmtrfkeras-0.0.1.dist-info/top_level.txt
filmtrfkeras-0.0.1.dist-info/RECORD
